odoo/addons/pos_cash_move_reason_multiple_control/README.rst
odoo/addons/pos_cash_move_reason_multiple_control/__init__.py
odoo/addons/pos_cash_move_reason_multiple_control/__manifest__.py
odoo/addons/pos_cash_move_reason_multiple_control/i18n/fr.po
odoo/addons/pos_cash_move_reason_multiple_control/i18n/pos_cash_move_reason_multiple_control.pot
odoo/addons/pos_cash_move_reason_multiple_control/readme/CONTRIBUTORS.rst
odoo/addons/pos_cash_move_reason_multiple_control/readme/DESCRIPTION.rst
odoo/addons/pos_cash_move_reason_multiple_control/static/description/icon.png
odoo/addons/pos_cash_move_reason_multiple_control/static/description/index.html
odoo/addons/pos_cash_move_reason_multiple_control/static/description/wizard_pos_move_reason_form.png
odoo/addons/pos_cash_move_reason_multiple_control/wizard/__init__.py
odoo/addons/pos_cash_move_reason_multiple_control/wizard/wizard_pos_move_reason.py
odoo/addons/pos_cash_move_reason_multiple_control/wizard/wizard_pos_move_reason.xml
odoo12_addon_pos_cash_move_reason_multiple_control-12.0.3.1.1.dist-info/METADATA
odoo12_addon_pos_cash_move_reason_multiple_control-12.0.3.1.1.dist-info/WHEEL
odoo12_addon_pos_cash_move_reason_multiple_control-12.0.3.1.1.dist-info/top_level.txt
odoo12_addon_pos_cash_move_reason_multiple_control-12.0.3.1.1.dist-info/RECORD
